AUTHORS
CHANGES
LICENSE
MANIFEST.in
Makefile
README.rst
setup.py
test_rbac.py
Flask_PRBAC.egg-info/PKG-INFO
Flask_PRBAC.egg-info/SOURCES.txt
Flask_PRBAC.egg-info/dependency_links.txt
Flask_PRBAC.egg-info/not-zip-safe
Flask_PRBAC.egg-info/requires.txt
Flask_PRBAC.egg-info/top_level.txt
docs/_themes/flask/layout.html
docs/_themes/flask/relations.html
docs/_themes/flask_small/layout.html
flask_prbac/__init__.py
flask_prbac/model.py