Metadata-Version: 1.1
Name: Flask-PRBAC
Version: 0.1.2
Summary: RBAC support for Flask
Home-page: https://github.com/tiantaozhang/flask-rbac
Author: tiantao zhang
Author-email: tatumnzhang@gmail.com
License: UNKNOWN
Platform: any
Classifier: Framework :: Flask
Classifier: Environment :: Web Environment
Classifier: License :: OSI Approved :: MIT License
Classifier: Operating System :: OS Independent
Classifier: Programming Language :: Python
Classifier: Programming Language :: Python :: 2
Classifier: Development Status :: 3 - Alpha
Classifier: Intended Audience :: Developers
Classifier: Topic :: Internet :: WWW/HTTP :: Dynamic Content
